batchsend/__init__.py
batchsend/batchsend.cpython-38-x86_64-linux-gnu.so
batchsend/batchsend.nim
batchsend/test.py
batchsend-0.3.5.data/scripts/__init__.py
batchsend-0.3.5.dist-info/LICENSE
batchsend-0.3.5.dist-info/METADATA
batchsend-0.3.5.dist-info/WHEEL
batchsend-0.3.5.dist-info/top_level.txt
batchsend-0.3.5.dist-info/RECORD
