Metadata-Version: 2.1
Name: batchsend
Version: 0.3.5
Summary: Nim / Python library to feed HTTP server quickly with custom messages
Home-page: https://github.com/marcomq/batchsend
Author: Marco Mengelkoch
Author-email: MMengelkoch@gmx.de
License: MIT
Keywords: nim,tcp,http-client
Platform: UNKNOWN
Classifier: Development Status :: 3 - Alpha
Classifier: Environment :: Console
Classifier: Programming Language :: Python
Classifier: Intended Audience :: Developers
Classifier: License :: OSI Approved :: MIT License
License-File: LICENSE
Requires-Dist: nimporter
